Metadata-Version: 2.1
Name: pygrobid
Version: 0.1.6
Summary: A python client for Grobid service
Home-page: https://github.com/wyh/pygrobid
Author: Samuel.Wu
Author-email: samuel.yh.wu@gmail.com
License: LICENSE
Platform: UNKNOWN
Classifier: Programming Language :: Python :: 3
Classifier: Operating System :: OS Independent
Requires-Python: >=3.6
